{
  "project_info": {
    "project_number": "305892888335",
    "project_id": "ticktick-4456a",
    "storage_bucket": "ticktick-4456a.firebasestorage.app"
  },
  "client": [
    {
      "client_info": {
        "mobilesdk_app_id": "1:305892888335:android:8e47f2d6d2a9d10b8cb87a",
        "android_client_info": {
          "package_name": "com.example.ticktick"
        }
      },
      "oauth_client": [],
      "api_key": [
        {
          "current_key": "AIzaSyAphy7p44ZU4BKjZxBblZnq2qJKPPERuLs"
        }
      ],
      "services": {
        "appinvite_service": {
          "other_platform_oauth_client": []
        }
      }
    }
  ],
  "configuration_version": "1"
}